Workbook

Sheet RLI14D3
B1: FORMATO RENTA LÍQUIDA IMPONIBLE 14 D PROPYME GENERAL
B2: (+) INGRESOS
B3: ▪ Ingresos Percibidos por Ventas y Exportaciones del Giro | I3: =+[1]Recuperado_Hoja1!$I$31 -> 0
B4: ▪ Ingresos por Rescate o Enajenación de Inversiones en Capitales Mobiliarios | I4: 0
B5: ▪ Ingresos por Enajenación de Participaciones en contratos de asociación o cuentas en participación | I5: 0
B6: ▪ Ingresos por Enajenación de Derechos Sociales y Acciones de Sociedades o cuotas de Fondos de inversión, no acogidos a los regímenes 14 A ni 14 D 3 | I6: 0
B7: ▪ Ingresos por Enajenación de Otros bienes no depreciables según la LIR | I7: 0 | J7: =SUM(I3:I7) -> 0
B9: (-) GASTOS Y EGRESOS
B10: ▪ Compras e Importaciones de Activos Fijos, Pagadas | I10: 0
B11: ▪ Compras e Importaciones de Existencias, Pagadas | I11: 0
B12: ▪ Servicios utilizados, Pagados | I12: 0
B13: ▪ Saldo Inicial de Activos Fijos, si se cambio desde Contabilidad Completa | I13: 0
B14: ▪ Saldo Inicial de Existencias, si se cambio desde Contabilidad Completa | I14: 0
B15: ▪ Remuneraciones y Honorarios Brutos, Pagados | I15: 0
B16: ▪ Intereses e Impuestos Pagados, que no sean de la LIR | I16: 0
B17: ▪ Pérdidas de Ejercicios Anteriores, sin Reajustar | I17: 0
B18: ▪ Cuotas pagadas en Compras al Crédito | I18: 0
B19: ▪ Costo en el Rescate o Enajenación de Inversiones en Capitales Mobiliarios (reajustado) | I19: 0
B20: ▪ Costo en la Enajenación de Participaciones en contratos de asociación o cuentas en participación (reajustado) | I20: 0
B21: ▪ Costo en la Enajenación de Derechos Sociales y Acciones de Sociedades o cuotas de Fondos de inversión (reajustado) | I21: 0
B22: ▪ Costo en la Enajenación de Otros bienes no depreciables según la LIR (reajustado) | I22: 0
B23: ▪ Otros gastos necesarios, según Artículo 31 LIR | I23: =+[1]Recuperado_Hoja1!$H$31 -> 30000485 | J23: =-SUM(I10:I23) -> -30000485
I25: RLI PREVIA | J25: =SUM(J23,J7) -> -30000485
I27: (-) Deducción por Beneficio al No Retiro, Art. 14 letra E | J27: =-'14E.14D3'!H12 -> 0
I29: RENTA LÍQUIDA IMPONIBLE AFECTA A 25% (O PÉRDIDA TRIBUTARIA) | J29: =SUM(J25:J27) -> -30000485
H31: IDPC | I31: 0.1 | J31: 0

Sheet 14E.14D3
B5: BENEFICIO 14E LIR
B7: RLI PREVIA | H7: =+RLI14D3!J25 -> -30000485
B8: (-) Retiros o Distribuciones del Ejercicio | H8: 0 | I8: Sin actualizar
B9: (-) Gastos Rechazados Art. 21 Inciso 2° LIR | H9: 0 | I9: Sin actualizar
D10: RENTA NO RETIRADA | H10: =+H7-H8-H9 -> -30000485
C12: BENEFICIO 14 E) LIR | D12: =IF(H10<0,0,H10) -> 0 | E12: x | F12: 0.5 | G12: = | H12: =+ROUND(D12*F12,0) -> 0
C14: TOPE | D14: 5000 | F14: 30991.74 | H14: =+D14*F14 -> 154958700

Sheet CPT14D3
B2: DETERMINACIÓN CAPITAL PROPIO 14 D3 al 31/12/2020
B4: (+) AGREGADOS
B5: ▪ Capital Aportado a la empresa, más su Aumentos Formales | D5: =+[1]Recuperado_Hoja1!$G$20 -> 1000000
B6: ▪ Bases Imponibles de Primera Categoría a lo largo de la vida de la empresa | D6: 0
B7: ▪ Beneficio artículo 14 letra E) LIR utilizado | D7: =-RLI14D3!J27 -> 0
B8: ▪ Rentas Percibidas con motivo de participaciones en otras empresas | D8: 0 | E8: =SUM(D5:D8) -> 1000000
B9: (-) DEDUCCIONES
B10: ▪ Disminuciones Formales de Capital | D10: 0
B11: ▪ Pérdidas Tributarias a lo largo de la vida de la empresa | D11: =+[1]Recuperado_Hoja1!$H$31 -> 30000485
B12: ▪ Gastos Rechazados Art. 21 Inc. 2°, pagados | D12: =+'14E.14D3'!H9 -> 0
B13: ▪ Retiros y Distribuciones pagadas a los propietarios | D13: 0 | E13: =-SUM(D10:D13) -> -30000485
C15: CAPITAL PROPIO al | D15: 44196 | E15: =SUM(E8:E13) -> -29000485

Sheet Rentas14D3
F1: DETERMINACIÓN DE RENTAS EMPRESARIALES AL | G1: 44561
A2: DETALLE | C2: CONTROL | D2: R.A.I. | E2: D.D.A.N. | F2: R.E.X. | I2: S.A.C. | L2: S.T.U.T.
F3: Rtas. Trib. Cumplida | G3: Rtas. Exentas IGC | H3: Ingresos No Renta | I3: Con Restitución | J3: Sin Rest. 2020 | K3: Sin Rest. 2016
I4: 0.369863 | J4: 0.333333 | K4: =IFERROR(TRUNC(K7/L7,6),0) -> 0
A5: Remanente Rentas Ejercicio Anterior | C5: =+D5 -> 0
A6: (+) C.M. Anual | B6: 0.067 | C6: =+D6 -> 0 | D6: =+ROUND(D5*$B6,0) -> 0 | E6: =+ROUND(E5*$B6,0) -> 0 | F6: =+ROUND(F5*$B6,0) -> 0 | G6: =+ROUND(G5*$B6,0) -> 0 | H6: =+ROUND(H5*$B6,0) -> 0 | I6: =+ROUND(I5*$B6,0) -> 0 | J6: =+ROUND(J5*$B6,0) -> 0 | K6: =+ROUND(K5*$B6,0) -> 0 | L6: =+ROUND(L5*$B6,0) -> 0
A7: Remanente Rentas Reajustado | C7: =SUM(C5:C6) -> 0 | D7: =SUM(D5:D6) -> 0 | E7: =SUM(E5:E6) -> 0 | F7: =SUM(F5:F6) -> 0 | G7: =SUM(G5:G6) -> 0 | H7: =SUM(H5:H6) -> 0 | I7: =SUM(I5:I6) -> 0 | J7: =SUM(J5:J6) -> 0 | ... L7: =SUM(L5:L6) -> 0
A9: (-) Ajuste Reverso RAI del | B9: =+G1-366 -> 44195 | C9: =+D9 -> 0 | D9: =-D7 -> 0
A10: Remanente Rentas Depurado | C10: =SUM(C7:C9) -> 0 | D10: =SUM(D7:D9) -> 0 | E10: =SUM(E7:E9) -> 0 | F10: =SUM(F7:F9) -> 0 | G10: =SUM(G7:G9) -> 0 | H10: =SUM(H7:H9) -> 0 | I10: =SUM(I7:I9) -> 0 | J10: =SUM(J7:J9) -> 0 | ... L10: =SUM(L7:L9) -> 0
A12: (+) R.A.I. determinado al | B12: =+G1 -> 44561
A13: CPT Final | B13: =+CPT14D3!E15 -> -29000485
A14: Retiros | B14: 0
A15: C. Propio Inicial | B15: 0
A16: REX | B16: =+F10+G10+H10 -> 0
B17: =+B13+B14-B15-B16 -> -29000485 | C17: =+D17 -> -29000485 | D17: =+B17 -> -29000485
A19: (+/-) Ajuste Diferencia Depreciación | C19: =+E19 -> 0 | E19: 0
A21: (+) Rentas exentas e Ingresos No Renta | C21: =+SUM(F21:H21) -> 0 | F21: 0 | G21: 0 | H21: 0
A23: (+) Crédito IDPC año actual | J23: =+RLI14D3!J31 -> 0
A24: (-) Crédito IDPC Gtos. Rech. | B24: 0 | J24: =-ROUND(B24*J4,0) -> 0
A25: (+) Créd. Divid. Percib. | J25: 0
A26: Rentas Antes de Imputaciones | C26: =SUM(C10:C25) -> -29000485 | D26: =SUM(D10:D25) -> -29000485 | E26: =SUM(E10:E25) -> 0 | F26: =SUM(F10:F25) -> 0 | G26: =SUM(G10:G25) -> 0 | H26: =SUM(H10:H25) -> 0 | I26: =SUM(I10:I25) -> 0 | J26: =SUM(J10:J25) -> 0 | ... L26: =SUM(L10:L25) -> 0
A28: (-) Retiros del Ejercicio | B28: 0 | C28: =+D28 -> 0 | D28: 0 | J28: 0 | K28: 0 | L28: 0
A29: Rentas antes de Exc. Retiros | C29: =SUM(C26:C28) -> -29000485 | D29: =SUM(D26:D28) -> -29000485 | E29: =SUM(E26:E28) -> 0 | F29: =SUM(F26:F28) -> 0 | G29: =SUM(G26:G28) -> 0 | H29: =SUM(H26:H28) -> 0 | I29: =SUM(I26:I28) -> 0 | J29: =SUM(J26:J28) -> 0 | ... L29: =SUM(L26:L28) -> 0
A31: (-) Exc. Retiros Ejerc Anterior | B31: 0
A32: REMANENTE RENTAS EJERC. SIGUIENTE | C32: =SUM(C29:C31) -> -29000485 | D32: =SUM(D29:D31) -> -29000485 | E32: =SUM(E29:E31) -> 0 | F32: =SUM(F29:F31) -> 0 | G32: =SUM(G29:G31) -> 0 | H32: =SUM(H29:H31) -> 0 | I32: =SUM(I29:I31) -> 0 | J32: =SUM(J29:J31) -> 0 | ... L32: =SUM(L29:L31) -> 0
A34: RETIROS DEL EJERCICIO NO IMPUTADOS | C34: =+B28+C28+L28 -> 0

Sheet Tributac (2)
A2: EMPRESA | D2: DUEÑO
A3: IDPC | D3: RETIROS | E3: 0
A4: PPM | D4: INCREMENTO | E4: 0
D5: BASE IGC | E5: =SUM(E3:E4) -> 0
A6: DEVOLUCION | B6: =+B3-B4 -> 0 | D6: IGC S/TABLA | E6: 0
D7: CRÉD IDPC | E7: =-E4 -> 0
D8: DEVOLUCION | E8: =SUM(E6:E7) -> 0
B10: PAGO O DEVOLUCION FINAL | D10: =+B6+E8 -> 0
