Workbook

Sheet Hoja1
B2: Préstamos Reales | D2: UF | F2: Préstamo | G2: Préstamos a Chilcos para Reconocimientos de Deuda | H2: UF | J2: UF | K2: Pesos
A3: 45406 | B3: JOPA a Chilcos | C3: 46000000 | D3: 1235.48 | F3: JOPA | G3: =C3+C4 -> 69000000 | H3: 1853.22 | I3: Préstamo JMP a Agrícola Los Chilcos | J3: =+D11+D20 -> 184.22 | K3: =+C11+C20 -> 7000000
B4: FHB a JOPA | C4: 23000000 | D4: 617.74
B5: PLS a Chilcos | C5: 46000000 | D5: 1235.5 | F5: PLS | G5: =C5+C6 -> 69000000 | H5: 1854.22
B6: FHB a PLS | C6: 23000000 | D6: 617.74 | I6: Préstamos JOPA a Agrícola Los Chilcos | J6: =+D3+D7+D15+D19 -> 2044.12 | K6: =+C3+C7+C15+C19 -> 76956300
A7: 45406 | B7: JOPA a Chilcos | C7: 2456300 | D7: 66 | F7: JOPA | G7: =C7 -> 2456300 | H7: 66
B8: FHB a JMP | C8: 1228150 | D8: 33 | F8: JMP | G8: =C8 -> 1228150 | H8: 33
B9: PLS a Chilcos | C9: 2456300 | D9: 66 | F9: PLS | G9: =C9+C10 -> 3684450 | H9: 99 | I9: Préstamo FHB a JMP | J9: =+D8+D12+D16+D21 -> 496.43 | K9: =+C8+C12+C16+C21 -> 18978150
B10: FHB a PLS | C10: 1228150 | D10: 33
A11: 45457 | B11: JMP a Chilcos | C11: 3000000 | D11: 80 | F11: JMP | G11: =C11+C12 -> 4500000 | H11: 120
B12: FHB a JMP | C12: 1500000 | D12: 40 | I12: Préstamo FHB a JOPA | J12: =+D4 -> 617.74 | K12: =+C4 -> 23000000
B13: PLS a Chilcos | C13: 3000000 | D13: 80 | F13: PLS | G13: =C13+C14 -> 4500000 | H13: 120
B14: FHB a PLS | C14: 1500000 | D14: 40
A15: 45636 | B15: JOPA a Chilcos | C15: 2500000 | D15: 65.16 | F15: JOPA | G15: =C15 -> 2500000 | H15: 65.16
B16: FHB a JMP | C16: 1250000 | D16: 32.58 | F16: JMP | G16: =C16 -> 1250000 | H16: 32.58
B17: PLS a Chilcos | C17: 2500000 | D17: 65.16 | F17: PLS | G17: 3750000 | H17: =D17+D18 -> 97.74
B18: FHB a PLS | C18: 1250000 | D18: 32.58
A19: 45691 | B19: JOPA a Chilcos | C19: 26000000 | D19: 677.48 | F19: JOPA | G19: =C19 -> 26000000 | H19: =D19 -> 677.48
B20: JMP a Chilcos | C20: 4000000 | D20: 104.22 | F20: JMP | G20: =C20+C21 -> 19000000 | H20: =D20+D21 -> 495.07
B21: FHB a JMP | C21: 15000000 | D21: 390.85
B22: PLS a Chilcos | C22: 30000000 | D22: 781.7 | F22: PLS | G22: =C22+C23 -> 45000000 | H22: =D22+D23 -> 1172.55
B23: FHB a PLS | C23: 15000000 | D23: 390.85

Sheet Dev Chilcos JOPA
A1: Préstamos JOPA a Agrícola Los Chilcos | B1: =+Hoja1!H3+Hoja1!H7+Hoja1!H15+Hoja1!H19 -> 2661.86 | C1: =+Hoja1!G3+Hoja1!G7+Hoja1!G15+Hoja1!G19 -> 99956300
A3: Detalle devoluciones
A4: Fecha | B4: UF día deposito | C4: Monto | D4: Monto UF | E4: Saldo
A5: 45863 | B5: 39209.42 | C5: 25000000 | D5: =+C5/B5 -> 637.60188 | E5: =+$B$1-D5 -> 2024.2581
A6: 45903 | B6: 39417.24 | C6: 10000000 | D6: =+C6/B6 -> 253.6961 | E6: =+E5-D6 -> 1770.562
A7: 45965 | B7: 39618.08 | C7: 10000000 | D7: =+C7/B7 -> 252.41001 | E7: =+E6-D7 -> 1518.152
A8: 45996 | B8: 39643.59 | C8: 6000000 | D8: =+C8/B8 -> 151.34855 | E8: =+E7-D8 -> 1366.8035
A9: 46038 | B9: 39744.55 | C9: 10689225 | D9: =+C9/B9 -> 268.9482 | E9: =+E8-D9 -> 1097.8553
A10: 46084 | B10: 39807.65 | C10: 7500000 | D10: =+C10/B10 -> 188.406 | E10: =+E9-D10 -> 909.44926
A11: 46133 | B11: 40000.61 | C11: 36367355 | D11: =+C11/B11 -> 909.17001 | E11: =+E10-D11 -> 0.279252

Sheet Dev Chilcos JMP
A1: Préstamo JMP a Agrícola Los Chilcos | B1: =+Hoja1!H8+Hoja1!H11+Hoja1!H16+Hoja1!H20 -> 680.65 | C1: =+Hoja1!G8+Hoja1!G11+Hoja1!G16+Hoja1!G20 -> 25978150
A3: Detalle devoluciones
A4: Fecha | B4: UF día deposito | C4: Monto | D4: Monto UF | E4: Saldo
A5: Pago Julio 25 $ | B5: 39194.21 | C5: -12500000 | D5: =+C5/B5 -> -318.92466 | E5: =+B1+D5 -> 361.72534
A6: Pago Sept 25 $ | B6: 39417.24 | C6: -5000000 | D6: =+C6/B6 -> -126.84805 | E6: =+E5+D6 -> 234.87729
A7: Pago 04 Nov 25 $ | B7: 39612.97 | C7: -5000000 | D7: =+C7/B7 -> -126.22129 | E7: =+E6+D7 -> 108.65601
A8: Pago 05 Dic 25 $ | B8: 39643.59 | C8: -3000000 | D8: =+C8/B8 -> -75.674277 | E8: =+E7+D8 -> 32.981731
A9: Pago 15 Ene 26 $ | B9: 39744.55 | C9: -1310775.3 | D9: =+C9/B9 -> -32.98 | E9: =+E8+D9 -> 0.0017309484

Sheet Dev JMP FHB
A1: Préstamo FHB a JMP | B1: =+Hoja1!D8+Hoja1!D12+Hoja1!D16+Hoja1!D21 -> 496.43 | C1: =+Hoja1!C8+Hoja1!C12+Hoja1!C16+Hoja1!C21 -> 18978150
A3: Detalle devoluciones
A4: Fecha | B4: Pesos | C4: UF día | D4: Monto UF | E4: Saldo
A5: 45863 | B5: 5000000 | C5: 39209.42 | D5: =+B5/C5 -> 127.52038 | E5: =+B1-D5 -> 368.90962
A6: 45865 | B6: 5000000 | C6: 39199.28 | D6: =+B6/C6 -> 127.55336 | E6: =+E5-D6 -> 241.35626
A7: 45866 | B7: 2500000 | C7: 39194.21 | D7: =+B7/C7 -> 63.784931 | E7: =+E6-D7 -> 177.57133
A8: 45903 | B8: 5000000 | C8: 39417.24 | D8: =+B8/C8 -> 126.84805 | E8: =+E7-D8 -> 50.72328
A9: 45965 | B9: 5000000 | C9: 39618.08 | D9: =+B9/C9 -> 126.20501 | E9: =+E8-D9 -> -75.481726
A10: 45996 | B10: 3000000 | C10: 39643.59 | D10: =+B10/C10 -> 75.674277 | E10: =+E9-D10 -> -151.156
A11: 46038 | B11: 1310775 | C11: 39744.55 | D11: =+B11/C11 -> 32.979993 | E11: =+E10-D11 -> -184.136

Sheet Dev JOPA FHB
A1: Préstamo FHB a JOPA | B1: =+Hoja1!J12 -> 617.74 | C1: =+Hoja1!K12 -> 23000000
A3: Detalle devoluciones
A4: Fecha | B4: Pesos | C4: UF día | D4: Monto UF | E4: Saldo
A5: 46038 | B5: 2689225 | C5: 39744.55 | D5: =+B5/C5 -> 67.662736 | E5: =+B1-D5 -> 550.07726
A6: 46084 | B6: 2500000 | C6: 39807.65 | D6: =+B6/C6 -> 62.801999 | E6: =+E5-D6 -> 487.27526
A7: 46133 | B7: 12122452 | C7: 40000.61 | D7: =+B7/C7 -> 303.05668 | E7: =+E6-D7 -> 184.21859
