Workbook
Name Polizas: Seguros!$B:$B
Name ReferenciaContactos: Contactos[ReferenciaContactos]
Name ReferenciaContactos: Contactos[ReferenciaContactos]
Name ReferenciaContactos: Contactos[ReferenciaContactos]
Name ReferenciaContactos: Contactos[ReferenciaContactos]
Name ReferenciaEmpresas: Empresas[[#All],[ReferenciaEmpresa]]
Name ReferenciaEmpresas: Empresas[[#All],[ReferenciaEmpresa]]
Name ReferenciaEmpresas: Empresas[[#All],[ReferenciaEmpresa]]
Name ReferenciaEmpresas: Empresas[[#All],[ReferenciaEmpresa]]
Name ReferenciaEquipos: Equipos[ReferenciaEquipos]
Name ReferenciaEquipos: Equipos[ReferenciaEquipos]
Name ReferenciaEquipos: Equipos[ReferenciaEquipos]
Name ReferenciaEquipos: Equipos[ReferenciaEquipos]
Name ReferenciaFacturas: Facturacion!$L:$L
Name Ubicaciones: Ubicacion[Ubicacion]
Name Ubicaciones: SEGUROS[Link]
Name Ubicaciones: Ubicacion[Ubicacion]
Name Ubicaciones: Ubicacion[Ubicacion]
Name UF_Julio_25: UF!$B$2

Sheet Equipos
A1: ID_Equipo | B1: Tipo_Equipo | C1: Marca | D1: Modelo | E1: Año | F1: Serie | G1: Patente | H1: Tipo de Energía | I1: Horometro inicial | J1: Fecha de Adquisición | K1: Costo de Adquisición | L1: Seguro | M1: Ultima mantencion preventiva | N1: Horometro | O1: ReferenciaEquipos
A2: E001 | B2: Alzahombre 12 Mts | C2: HAULOTTE | D2: Compact 12 | E2: 2021 | F2: GAM-39133 | H2: Electrico | I2: 1200 | J2: 45504 | K2: 10000000 | L2: POLIZA 223 HDI | M2: =_xlfn.MAXIFS(Mantenimientos!D:D, Mantenimientos!B:B, "*"&A2&"*", Mantenimientos!E:E, "Preventivo") -> 45916 | N2: {=LOOKUP(2, 1/(ISNUMBER(SEARCH(A2, Horometro!A:A))), Horometro!C:C)} -> 2000 | O2: =_xlfn.TEXTJOIN(" - ", TRUE, A2, B2, C2) -> E001 - Alzahombre 12 Mts - HAULOTTE
A3: E002 | B3: Alzahombre 12 Mts | C3: JLG | D3: R3246 | E3: 2021 | F3: M200048234 | H3: Electrico | I3: 0 | J3: 44484 | M3: =_xlfn.MAXIFS(Mantenimientos!D:D, Mantenimientos!B:B, "*"&A3&"*", Mantenimientos!E:E, "Preventivo") -> 0 | N3: {=LOOKUP(2, 1/(ISNUMBER(SEARCH(A3, Horometro!A:A))), Horometro!C:C)} -> 30 | O3: =_xlfn.TEXTJOIN(" - ", TRUE, A3, B3, C3) -> E002 - Alzahombre 12 Mts - JLG
A4: E003 | B4: Alzahombre 12 Mts | C4: JLG | D4: R3246 | E4: 2021 | F4: M200048412 | H4: Electrico | J4: 44484 | M4: =_xlfn.MAXIFS(Mantenimientos!D:D, Mantenimientos!B:B, "*"&A4&"*", Mantenimientos!E:E, "Preventivo") -> 0 | N4: {=LOOKUP(2, 1/(ISNUMBER(SEARCH(A4, Horometro!A:A))), Horometro!C:C)} -> 5662 | O4: =_xlfn.TEXTJOIN(" - ", TRUE, A4, B4, C4) -> E003 - Alzahombre 12 Mts - JLG
A5: E004 | B5: Alzahombre 12 Mts | C5: JLG | D5: R3246 | E5: 2021 | F5: M200050340 | H5: Electrico | J5: 44515 | M5: =_xlfn.MAXIFS(Mantenimientos!D:D, Mantenimientos!B:B, "*"&A5&"*", Mantenimientos!E:E, "Preventivo") -> 0 | N5: {=LOOKUP(2, 1/(ISNUMBER(SEARCH(A5, Horometro!A:A))), Horometro!C:C)} -> #N/A | O5: =_xlfn.TEXTJOIN(" - ", TRUE, A5, B5, C5) -> E004 - Alzahombre 12 Mts - JLG
A6: E005 | B6: Alzahombre 10 Mts | C6: SNORKEL | D6: S3226E | E6: 2017 | F6: S170800196A | H6: Electrico | J6: 44529 | M6: =_xlfn.MAXIFS(Mantenimientos!D:D, Mantenimientos!B:B, "*"&A6&"*", Mantenimientos!E:E, "Preventivo") -> 0 | N6: {=LOOKUP(2, 1/(ISNUMBER(SEARCH(A6, Horometro!A:A))), Horometro!C:C)} -> #N/A | O6: =_xlfn.TEXTJOIN(" - ", TRUE, A6, B6, C6) -> E005 - Alzahombre 10 Mts - SNORKEL
A7: E006 | B7: Alzahombre 14 Mts | C7: SKYJACK | D7: SJIII 4740 | E7: 2020 | F7: 70205122 | H7: Electrico | J7: 45582 | M7: =_xlfn.MAXIFS(Mantenimientos!D:D, Mantenimientos!B:B, "*"&A7&"*", Mantenimientos!E:E, "Preventivo") -> 0 | N7: {=LOOKUP(2, 1/(ISNUMBER(SEARCH(A7, Horometro!A:A))), Horometro!C:C)} -> #N/A | O7: =_xlfn.TEXTJOIN(" - ", TRUE, A7, B7, C7) -> E006 - Alzahombre 14 Mts - SKYJACK
A8: E007 | B8: Alzahombre 12 Mts | C8: JLG | D8: R3246 | E8: 2022 | F8: M200050660 | H8: Electrico | J8: 44636 | M8: =_xlfn.MAXIFS(Mantenimientos!D:D, Mantenimientos!B:B, "*"&A8&"*", Mantenimientos!E:E, "Preventivo") -> 0 | N8: {=LOOKUP(2, 1/(ISNUMBER(SEARCH(A8, Horometro!A:A))), Horometro!C:C)} -> #N/A | O8: =_xlfn.TEXTJOIN(" - ", TRUE, A8, B8, C8) -> E007 - Alzahombre 12 Mts - JLG
A9: E008 | B9: Alzahombre 12 Mts | C9: SNORKEL | D9: S4732E | E9: 2023 | F9: 230101014 | H9: Electrico | J9: 45729 | M9: =_xlfn.MAXIFS(Mantenimientos!D:D, Mantenimientos!B:B, "*"&A9&"*", Mantenimientos!E:E, "Preventivo") -> 0 | N9: {=LOOKUP(2, 1/(ISNUMBER(SEARCH(A9, Horometro!A:A))), Horometro!C:C)} -> #N/A | O9: =_xlfn.TEXTJOIN(" - ", TRUE, A9, B9, C9) -> E008 - Alzahombre 12 Mts - SNORKEL
A10: E009 | B10: Brazo Articulado 16 MTS | C10: SNORKEL | D10: A46JRT | E10: 2019 | F10: 1906000199 | H10: Diesel | J10: 44825 | M10: =_xlfn.MAXIFS(Mantenimientos!D:D, Mantenimientos!B:B, "*"&A10&"*", Mantenimientos!E:E, "Preventivo") -> 0 | N10: {=LOOKUP(2, 1/(ISNUMBER(SEARCH(A10, Horometro!A:A))), Horometro!C:C)} -> #N/A | O10: =_xlfn.TEXTJOIN(" - ", TRUE, A10, B10, C10) -> E009 - Brazo Articulado 16 MTS - SNORKEL
A11: E010 | B11: Brazo Articulado 16 MTS | C11: JLG | D11: 450AJ | E11: 2023 | F11: 300300738 | H11: Diesel | J11: 45043 | M11: =_xlfn.MAXIFS(Mantenimientos!D:D, Mantenimientos!B:B, "*"&A11&"*", Mantenimientos!E:E, "Preventivo") -> 0 | N11: {=LOOKUP(2, 1/(ISNUMBER(SEARCH(A11, Horometro!A:A))), Horometro!C:C)} -> #N/A | O11: =_xlfn.TEXTJOIN(" - ", TRUE, A11, B11, C11) -> E010 - Brazo Articulado 16 MTS - JLG
A12: E011 | B12: Grua Horquilla | C12: TOYOTA | D12: FGZN25 | E12: 2023 | F12: 40227 | H12: Gas | J12: 45160 | M12: =_xlfn.MAXIFS(Mantenimientos!D:D, Mantenimientos!B:B, "*"&A12&"*", Mantenimientos!E:E, "Preventivo") -> 45852 | N12: {=LOOKUP(2, 1/(ISNUMBER(SEARCH(A12, Horometro!A:A))), Horometro!C:C)} -> #N/A | O12: =_xlfn.TEXTJOIN(" - ", TRUE, A12, B12, C12) -> E011 - Grua Horquilla - TOYOTA
A13: E012 | B13: Grua Horquilla | C13: TOYOTA | D13: FGZN25 | E13: 2024 | F13: 40271 | H13: Gas | J13: 45287 | M13: =_xlfn.MAXIFS(Mantenimientos!D:D, Mantenimientos!B:B, "*"&A13&"*", Mantenimientos!E:E, "Preventivo") -> 0 | N13: {=LOOKUP(2, 1/(ISNUMBER(SEARCH(A13, Horometro!A:A))), Horometro!C:C)} -> #N/A | O13: =_xlfn.TEXTJOIN(" - ", TRUE, A13, B13, C13) -> E012 - Grua Horquilla - TOYOTA
A14: E013 | B14: Grua Horquilla | C14: TOYOTA | D14: FGZN25 | E14: 2024 | F14: 24819 | H14: Gas | J14: 45406 | M14: =_xlfn.MAXIFS(Mantenimientos!D:D, Mantenimientos!B:B, "*"&A14&"*", Mantenimientos!E:E, "Preventivo") -> 0 | N14: {=LOOKUP(2, 1/(ISNUMBER(SEARCH(A14, Horometro!A:A))), Horometro!C:C)} -> #N/A | O14: =_xlfn.TEXTJOIN(" - ", TRUE, A14, B14, C14) -> E013 - Grua Horquilla - TOYOTA
A15: E014 | B15: Grua Horquilla | C15: TOYOTA | D15: FGZN25 | E15: 2024 | F15: 40063 | H15: Gas | J15: 45406 | M15: =_xlfn.MAXIFS(Mantenimientos!D:D, Mantenimientos!B:B, "*"&A15&"*", Mantenimientos!E:E, "Preventivo") -> 0 | N15: {=LOOKUP(2, 1/(ISNUMBER(SEARCH(A15, Horometro!A:A))), Horometro!C:C)} -> #N/A | O15: =_xlfn.TEXTJOIN(" - ", TRUE, A15, B15, C15) -> E014 - Grua Horquilla - TOYOTA
A16: E015 | B16: Grua Horquilla | C16: TOYOTA | D16: FGZN25 | E16: 2024 | F16: 40020 | H16: Gas | J16: 45406 | M16: =_xlfn.MAXIFS(Mantenimientos!D:D, Mantenimientos!B:B, "*"&A16&"*", Mantenimientos!E:E, "Preventivo") -> 0 | N16: {=LOOKUP(2, 1/(ISNUMBER(SEARCH(A16, Horometro!A:A))), Horometro!C:C)} -> #N/A | O16: =_xlfn.TEXTJOIN(" - ", TRUE, A16, B16, C16) -> E015 - Grua Horquilla - TOYOTA
A17: E016 | B17: Grua Horquilla | C17: TOYOTA | D17: FGZN25 | E17: 2024 | F17: 40067 | H17: Gas | J17: 45406 | M17: =_xlfn.MAXIFS(Mantenimientos!D:D, Mantenimientos!B:B, "*"&A17&"*", Mantenimientos!E:E, "Preventivo") -> 0 | N17: {=LOOKUP(2, 1/(ISNUMBER(SEARCH(A17, Horometro!A:A))), Horometro!C:C)} -> #N/A | O17: =_xlfn.TEXTJOIN(" - ", TRUE, A17, B17, C17) -> E016 - Grua Horquilla - TOYOTA
A18: E017 | B18: Grua Horquilla | C18: TOYOTA | D18: FGZN25 | E18: 2025 | F18: 40550 | H18: Gas | J18: 45741 | M18: =_xlfn.MAXIFS(Mantenimientos!D:D, Mantenimientos!B:B, "*"&A18&"*", Mantenimientos!E:E, "Preventivo") -> 0 | N18: {=LOOKUP(2, 1/(ISNUMBER(SEARCH(A18, Horometro!A:A))), Horometro!C:C)} -> #N/A | O18: =_xlfn.TEXTJOIN(" - ", TRUE, A18, B18, C18) -> E017 - Grua Horquilla - TOYOTA
A19: E018 | B19: Grua Horquilla | C19: TOYOTA | D19: FGZN25 | E19: 2025 | F19: 40555 | H19: Gas | J19: 45741 | M19: =_xlfn.MAXIFS(Mantenimientos!D:D, Mantenimientos!B:B, "*"&A19&"*", Mantenimientos!E:E, "Preventivo") -> 0 | N19: {=LOOKUP(2, 1/(ISNUMBER(SEARCH(A19, Horometro!A:A))), Horometro!C:C)} -> #N/A | O19: =_xlfn.TEXTJOIN(" - ", TRUE, A19, B19, C19) -> E018 - Grua Horquilla - TOYOTA
A20: E019 | B20: Grua Horquilla | C20: TOYOTA | D20: FGZN25 | E20: 2025 | F20: 40557 | H20: Gas | J20: 45741 | M20: =_xlfn.MAXIFS(Mantenimientos!D:D, Mantenimientos!B:B, "*"&A20&"*", Mantenimientos!E:E, "Preventivo") -> 0 | N20: {=LOOKUP(2, 1/(ISNUMBER(SEARCH(A20, Horometro!A:A))), Horometro!C:C)} -> #N/A | O20: =_xlfn.TEXTJOIN(" - ", TRUE, A20, B20, C20) -> E019 - Grua Horquilla - TOYOTA
... A28: E027 | B28: Grua Horquilla | C28: TOYOTA | D28: FGZN25 | E28: 2025 | F28: 40733 | H28: Gas | J28: 45862 | M28: =_xlfn.MAXIFS(Mantenimientos!D:D, Mantenimientos!B:B, "*"&A28&"*", Mantenimientos!E:E, "Preventivo") -> 0 | N28: {=LOOKUP(2, 1/(ISNUMBER(SEARCH(A28, Horometro!A:A))), Horometro!C:C)} -> #N/A | O28: =_xlfn.TEXTJOIN(" - ", TRUE, A28, B28, C28) -> E027 - Grua Horquilla - TOYOTA
A29: S001 | B29: Brazo Articulado 16 MTS GAM | C29: Snorkel | H29: Diesel | M29: =_xlfn.MAXIFS(Mantenimientos!D:D, Mantenimientos!B:B, "*"&A29&"*", Mantenimientos!E:E, "Preventivo") -> 0 | N29: {=LOOKUP(2, 1/(ISNUMBER(SEARCH(A29, Horometro!A:A))), Horometro!C:C)} -> 6400 | O29: =_xlfn.TEXTJOIN(" - ", TRUE, A29, B29, C29) -> S001 - Brazo Articulado 16 MTS GAM - Snorkel
A30: S002 | B30: Tijera 10mts GAM | C30: Snorkel | H30: Electrico | M30: =_xlfn.MAXIFS(Mantenimientos!D:D, Mantenimientos!B:B, "*"&A30&"*", Mantenimientos!E:E, "Preventivo") -> 0 | N30: {=LOOKUP(2, 1/(ISNUMBER(SEARCH(A30, Horometro!A:A))), Horometro!C:C)} -> #N/A | O30: =_xlfn.TEXTJOIN(" - ", TRUE, A30, B30, C30) -> S002 - Tijera 10mts GAM - Snorkel
N31: {=LOOKUP(2, 1/(ISNUMBER(SEARCH(A31, Horometro!A:A))), Horometro!C:C)} -> 5662 | O31: =_xlfn.TEXTJOIN(" - ", TRUE, A31, B31, C31)
N32: {=LOOKUP(2, 1/(ISNUMBER(SEARCH(A32, Horometro!A:A))), Horometro!C:C)} -> 5662 | O32: =_xlfn.TEXTJOIN(" - ", TRUE, A32, B32, C32)
N33: {=LOOKUP(2, 1/(ISNUMBER(SEARCH(A33, Horometro!A:A))), Horometro!C:C)} -> 5662 | O33: =_xlfn.TEXTJOIN(" - ", TRUE, A33, B33, C33)
N34: {=LOOKUP(2, 1/(ISNUMBER(SEARCH(A34, Horometro!A:A))), Horometro!C:C)} -> 5662 | O34: =_xlfn.TEXTJOIN(" - ", TRUE, A34, B34, C34)
N35: {=LOOKUP(2, 1/(ISNUMBER(SEARCH(A35, Horometro!A:A))), Horometro!C:C)} -> 5662 | O35: =_xlfn.TEXTJOIN(" - ", TRUE, A35, B35, C35)
N36: {=LOOKUP(2, 1/(ISNUMBER(SEARCH(A36, Horometro!A:A))), Horometro!C:C)} -> 5662 | O36: =_xlfn.TEXTJOIN(" - ", TRUE, A36, B36, C36)
N37: {=LOOKUP(2, 1/(ISNUMBER(SEARCH(A37, Horometro!A:A))), Horometro!C:C)} -> 5662 | O37: =_xlfn.TEXTJOIN(" - ", TRUE, A37, B37, C37)
N38: {=LOOKUP(2, 1/(ISNUMBER(SEARCH(A38, Horometro!A:A))), Horometro!C:C)} -> 5662 | O38: =_xlfn.TEXTJOIN(" - ", TRUE, A38, B38, C38)
N39: {=LOOKUP(2, 1/(ISNUMBER(SEARCH(A39, Horometro!A:A))), Horometro!C:C)} -> 5662 | O39: =_xlfn.TEXTJOIN(" - ", TRUE, A39, B39, C39)
N40: {=LOOKUP(2, 1/(ISNUMBER(SEARCH(A40, Horometro!A:A))), Horometro!C:C)} -> 5662 | O40: =_xlfn.TEXTJOIN(" - ", TRUE, A40, B40, C40)
N41: {=LOOKUP(2, 1/(ISNUMBER(SEARCH(A41, Horometro!A:A))), Horometro!C:C)} -> 5662 | O41: =_xlfn.TEXTJOIN(" - ", TRUE, A41, B41, C41)
N42: {=LOOKUP(2, 1/(ISNUMBER(SEARCH(A42, Horometro!A:A))), Horometro!C:C)} -> 5662 | O42: =_xlfn.TEXTJOIN(" - ", TRUE, A42, B42, C42)
... N355: {=LOOKUP(2, 1/(ISNUMBER(SEARCH(A355, Horometro!A:A))), Horometro!C:C)} -> 5662 | O355: =_xlfn.TEXTJOIN(" - ", TRUE, A355, B355, C355)

Sheet Arriendos
A1: ID_Arriendo | B1: Empresa | C1: Equipo | D1: Ubicacion | E1: Fecha_Inicio | F1: Fecha _Termino | G1: Tarifa_Diaria | H1: Días_Totales | I1: Monto_Neto _Total | J1: Monto_con_IVA | K1: Pesos | L1: Factura | M1: Notas
A2: AR001 | B2: BODEGAS SAN FRANCISCO LIMITADA | C2: E020 - Grua Horquilla - TOYOTA | D2: Puerto Madero | E2: 45839 | F2: 45869 | G2: =16.5/20 -> 0.825 | H2: =+Arriendos[[#This Row],[Fecha _Termino]]-Arriendos[[#This Row],[Fecha_Inicio]] -> 30 | I2: =+Arriendos[[#This Row],[Días_Totales]]*Arriendos[[#This Row],[Tarifa_Diaria]] -> 24.75 | J2: =+Arriendos[[#This Row],[Monto_Neto _Total]]*1.19 -> 29.4525 | K2: =+Arriendos[[#This Row],[Monto_con_IVA]]*UF_Julio_25 -> 1154069.1 | L2: Ingreso - 12-Aug-2025 - MOV001 - BODEGAS SAN FRANCISCO LIMITADA - 201
A3: AR002 | B3: HITES | C3: E005 - Alzahombre 10 Mts - SNORKEL | D3: Bodega 10 | E3: 45841 | F3: 45869 | G3: =15/20 -> 0.75 | H3: =+Arriendos[[#This Row],[Fecha _Termino]]-Arriendos[[#This Row],[Fecha_Inicio]] -> 28 | I3: =+Arriendos[[#This Row],[Días_Totales]]*Arriendos[[#This Row],[Tarifa_Diaria]] -> 21 | J3: =+Arriendos[[#This Row],[Monto_Neto _Total]]*1.19 -> 24.99 | K3: =+Arriendos[[#This Row],[Monto_con_IVA]]*UF_Julio_25 -> 979210.16 | L3: Ingreso - 12-Aug-2025 - MOV001 - BODEGAS SAN FRANCISCO LIMITADA - 201
A4: AR003 | B4: FALABELLA | C4: S001 - Brazo Articulado 16 MTS GAM - Snorkel | D4: Bodega 15 | E4: 45845 | F4: 45869 | G4: =30/20 -> 1.5 | H4: =+Arriendos[[#This Row],[Fecha _Termino]]-Arriendos[[#This Row],[Fecha_Inicio]] -> 24 | I4: =+Arriendos[[#This Row],[Días_Totales]]*Arriendos[[#This Row],[Tarifa_Diaria]] -> 36 | J4: =+Arriendos[[#This Row],[Monto_Neto _Total]]*1.19 -> 42.84 | K4: =+Arriendos[[#This Row],[Monto_con_IVA]]*UF_Julio_25 -> 1678646
A5: AR004 | C5: S001 - Brazo Articulado 16 MTS GAM - Snorkel | D5: Bodega 15 | G5: 2 | H5: 30 | I5: =+Arriendos[[#This Row],[Días_Totales]]*Arriendos[[#This Row],[Tarifa_Diaria]] -> 60 | J5: =+Arriendos[[#This Row],[Monto_Neto _Total]]*1.19 -> 71.4 | K5: =+Arriendos[[#This Row],[Monto_con_IVA]]*UF_Julio_25 -> 2797743.3
A6: AR005 | H6: =+Arriendos[[#This Row],[Fecha _Termino]]-Arriendos[[#This Row],[Fecha_Inicio]] -> 0 | I6: =+Arriendos[[#This Row],[Días_Totales]]*Arriendos[[#This Row],[Tarifa_Diaria]] -> 0 | J6: =+Arriendos[[#This Row],[Monto_Neto _Total]]*1.19 -> 0 | K6: =+Arriendos[[#This Row],[Monto_con_IVA]]*UF_Julio_25 -> 0
A7: AR006 | H7: =+Arriendos[[#This Row],[Fecha _Termino]]-Arriendos[[#This Row],[Fecha_Inicio]] -> 0 | I7: =+Arriendos[[#This Row],[Días_Totales]]*Arriendos[[#This Row],[Tarifa_Diaria]] -> 0 | J7: =+Arriendos[[#This Row],[Monto_Neto _Total]]*1.19 -> 0 | K7: =+Arriendos[[#This Row],[Monto_con_IVA]]*UF_Julio_25 -> 0
A8: AR007 | H8: =+Arriendos[[#This Row],[Fecha _Termino]]-Arriendos[[#This Row],[Fecha_Inicio]] -> 0 | I8: =+Arriendos[[#This Row],[Días_Totales]]*Arriendos[[#This Row],[Tarifa_Diaria]] -> 0 | J8: =+Arriendos[[#This Row],[Monto_Neto _Total]]*1.19 -> 0 | K8: =+Arriendos[[#This Row],[Monto_con_IVA]]*UF_Julio_25 -> 0
A9: AR008 | H9: =+Arriendos[[#This Row],[Fecha _Termino]]-Arriendos[[#This Row],[Fecha_Inicio]] -> 0 | I9: =+Arriendos[[#This Row],[Días_Totales]]*Arriendos[[#This Row],[Tarifa_Diaria]] -> 0 | J9: =+Arriendos[[#This Row],[Monto_Neto _Total]]*1.19 -> 0 | K9: =+Arriendos[[#This Row],[Monto_con_IVA]]*UF_Julio_25 -> 0
A10: AR009 | H10: =+Arriendos[[#This Row],[Fecha _Termino]]-Arriendos[[#This Row],[Fecha_Inicio]] -> 0 | I10: =+Arriendos[[#This Row],[Días_Totales]]*Arriendos[[#This Row],[Tarifa_Diaria]] -> 0 | J10: =+Arriendos[[#This Row],[Monto_Neto _Total]]*1.19 -> 0 | K10: =+Arriendos[[#This Row],[Monto_con_IVA]]*UF_Julio_25 -> 0

Sheet Subarriendos
A1: ID_Subarriendo | B1: Empresa | C1: ID_Equipo | D1: Fecha Inicio | E1: Fecha Término | F1: Tarifa Diaria | G1: Días Totales | H1: Monto_Neto _Total | I1: Monto_con_IVA | J1: Pesos | K1: Factura | L1: Notas
A2: SAR001 | B2: GAM | C2: S001 - Brazo Articulado 16 MTS GAM - Snorkel | D2: 45845 | E2: 45869 | F2: 1 | G2: =+E2-D2 -> 24 | H2: =+G2*F2 -> 24 | I2: =+Subarriendos[[#This Row],[Monto_Neto _Total]]*1.19 -> 28.56 | J2: =+Subarriendos[[#This Row],[Monto_con_IVA]]*UF_Julio_25 -> 1119097.3
A3: SAR002 | B3: BANCO DE CHILE | G3: =+E3-D3 -> 0 | H3: =+G3*F3 -> 0 | I3: =+Subarriendos[[#This Row],[Monto_Neto _Total]]*1.19 -> 0 | J3: =+Subarriendos[[#This Row],[Monto_con_IVA]]*UF_Julio_25 -> 0
A4: SAR003 | G4: =+E4-D4 -> 0 | H4: =+G4*F4 -> 0 | I4: =+Subarriendos[[#This Row],[Monto_Neto _Total]]*1.19 -> 0 | J4: =+Subarriendos[[#This Row],[Monto_con_IVA]]*UF_Julio_25 -> 0
A5: SAR004 | G5: =+E5-D5 -> 0 | H5: =+G5*F5 -> 0 | I5: =+Subarriendos[[#This Row],[Monto_Neto _Total]]*1.19 -> 0 | J5: =+Subarriendos[[#This Row],[Monto_con_IVA]]*UF_Julio_25 -> 0
A6: SAR005 | G6: =+E6-D6 -> 0 | H6: =+G6*F6 -> 0 | I6: =+Subarriendos[[#This Row],[Monto_Neto _Total]]*1.19 -> 0 | J6: =+Subarriendos[[#This Row],[Monto_con_IVA]]*UF_Julio_25 -> 0
A7: SAR006 | G7: =+E7-D7 -> 0 | H7: =+G7*F7 -> 0 | I7: =+Subarriendos[[#This Row],[Monto_Neto _Total]]*1.19 -> 0 | J7: =+Subarriendos[[#This Row],[Monto_con_IVA]]*UF_Julio_25 -> 0
A8: SAR007 | G8: =+E8-D8 -> 0 | H8: =+G8*F8 -> 0 | I8: =+Subarriendos[[#This Row],[Monto_Neto _Total]]*1.19 -> 0 | J8: =+Subarriendos[[#This Row],[Monto_con_IVA]]*UF_Julio_25 -> 0
A9: SAR008 | G9: =+E9-D9 -> 0 | H9: =+G9*F9 -> 0 | I9: =+Subarriendos[[#This Row],[Monto_Neto _Total]]*1.19 -> 0 | J9: =+Subarriendos[[#This Row],[Monto_con_IVA]]*UF_Julio_25 -> 0
A10: SAR009 | G10: =+E10-D10 -> 0 | H10: =+G10*F10 -> 0 | I10: =+Subarriendos[[#This Row],[Monto_Neto _Total]]*1.19 -> 0 | J10: =+Subarriendos[[#This Row],[Monto_con_IVA]]*UF_Julio_25 -> 0

Sheet Mantenimientos
A1: ID_Mantenimiento | B1: Equipo | C1: Fecha Inicio | D1: Fecha Termino | E1: Preventivo/Reparacion | F1: Monto_Neto | G1: Mano Obra | H1: Materiales | I1: Monto_Con_IVA | J1: Comentario
A2: MAN001 | B2: E011 - Grua Horquilla - TOYOTA | C2: 45850 | D2: 45852 | E2: Preventivo | F2: 150000 | G2: 50000 | H2: 50000 | I2: =+Mantenimientos[[#This Row],[Monto_Neto]]*1.19 -> 178500 | J2: Cambio aceite
A3: MAN002 | B3: E004 - Alzahombre 12 Mts - JLG | C3: 45853 | D3: 45853 | E3: Reparacion | F3: 300000 | G3: 200000 | H3: 100000 | I3: =+Mantenimientos[[#This Row],[Monto_Neto]]*1.19 -> 357000 | J3: Liquido baterias
A4: MAN003 | B4: E001 - Alzahombre 12 Mts - HAULOTTE | C4: 45853 | D4: 45915 | E4: Preventivo | I4: =+Mantenimientos[[#This Row],[Monto_Neto]]*1.19 -> 0
A5: MAN004 | B5: E001 - Alzahombre 12 Mts - HAULOTTE | C5: 45853 | D5: 45916 | E5: Reparacion | I5: =+Mantenimientos[[#This Row],[Monto_Neto]]*1.19 -> 0
A6: MAN005 | B6: E001 - Alzahombre 12 Mts - HAULOTTE | C6: 45853 | D6: 45916 | E6: Preventivo | I6: =+Mantenimientos[[#This Row],[Monto_Neto]]*1.19 -> 0
A7: MAN006 | I7: =+Mantenimientos[[#This Row],[Monto_Neto]]*1.19 -> 0
A8: MAN007 | I8: =+Mantenimientos[[#This Row],[Monto_Neto]]*1.19 -> 0
A9: MAN008 | I9: =+Mantenimientos[[#This Row],[Monto_Neto]]*1.19 -> 0
A10: MAN009 | I10: =+Mantenimientos[[#This Row],[Monto_Neto]]*1.19 -> 0

Sheet Transportes
A1: ID_Transporte | B1: Fecha | C1: Equipo | D1: Origen | E1: Destino | F1: Factura transportista EGRESO | G1: Factura Cliente INGRESO | H1: Nota
A2: T001 | B2: 45840 | C2: E001 - Alzahombre 12 Mts - HAULOTTE | D2: Puerto Madero | E2: Bodega 10 | F2: Egreso - 12-Aug-2025 - MOV002 - BODEGAS SAN FRANCISCO LIMITADA - 5213 | G2: Ingreso - 00-Jan-1900 - MOV004 - FALABELLA - 3265
A3: T002 | B3: 45846 | C3: E010 - Brazo Articulado 16 MTS - JLG
A4: T003
A5: T004
A6: T005
A7: T006
A8: T007
A9: T008
A10: T009

Sheet Horometro
A1: Equipo | B1: Fecha | C1: Horas
A2: E001 - Alzahombre 12 Mts - HAULOTTE | B2: 45836 | C2: 2000
A3: E024 - Grua Horquilla - TOYOTA | B3: 45836 | C3: 3500
A4: S001 - Brazo Articulado 16 MTS GAM - Snorkel | B4: 45806 | C4: 6400
A5: E002 - Alzahombre 12 Mts - JLG | B5: 45837 | C5: 30
A6: E003 - Alzahombre 12 Mts - JLG | B6: 45838 | C6: 5662

Sheet Empresas
A1: ID_Empresa | B1: Tipo | C1: Nombre_Empresa | D1: RUT | E1: Notas | F1: ReferenciaEmpresa
A2: EM001 | B2: Cliente | C2: BODEGAS SAN FRANCISCO LIMITADA | D2: 76988780-6 | F2: =_xlfn.TEXTJOIN(" - ", TRUE, , C2, ) -> BODEGAS SAN FRANCISCO LIMITADA
A3: EM002 | B3: Proveedor | C3: ASESORIAS ECOX LIMITADA | D3: 55.555.555-5 | F3: =_xlfn.TEXTJOIN(" - ", TRUE, , C3, ) -> ASESORIAS ECOX LIMITADA
A4: EM003 | B4: Proveedor | C4: GAM | D4: 55.555.555-5 | F4: =_xlfn.TEXTJOIN(" - ", TRUE, , C4, ) -> GAM
A5: EM004 | B5: Proveedor | C5: BANCO DE CHILE | D5: 54.222.222 | F5: =_xlfn.TEXTJOIN(" - ", TRUE, , C5, ) -> BANCO DE CHILE
A6: EM005 | B6: Proveedor | C6: DOMINIQUE HIRIART | D6: 15.555.555-5 | F6: =_xlfn.TEXTJOIN(" - ", TRUE, , C6, ) -> DOMINIQUE HIRIART
A7: EM006 | B7: Cliente | C7: HITES | D7: 44.444.444-4 | F7: =_xlfn.TEXTJOIN(" - ", TRUE, , C7, ) -> HITES
A8: EM007 | B8: Cliente | C8: FALABELLA | D8: 33.333.333-3 | F8: =_xlfn.TEXTJOIN(" - ", TRUE, , C8, ) -> FALABELLA
A9: EM008 | B9: Proveedor | C9: HORIZON | D9: 22.222.222-2 | F9: =_xlfn.TEXTJOIN(" - ", TRUE, , C9, ) -> HORIZON
A10: EM009 | F10: =_xlfn.TEXTJOIN(" - ", TRUE, , C10, )

Sheet Contactos
A1: ID_Contactos | B1: Empresa | C1: Nombre | D1: Apellido1 | E1: Apellido2 | F1: Mail | G1: Telefono | H1: ReferenciaContactos
A2: Con001 | B2: ASESORIAS ECOX LIMITADA | C2: Pedro | D2: Lecaros | E2: Sotomayor | F2: pedro@ecox.cl | G2: 56215654658 | H2: =_xlfn.TEXTJOIN(" ", TRUE,C2,D2) -> Pedro Lecaros
A3: Con002 | B3: BODEGAS SAN FRANCISCO LIMITADA | C3: Juan | D3: Perez | E3: Pereira | F3: juan@bsf.cl | G3: 56215654658 | H3: =_xlfn.TEXTJOIN(" ", TRUE,C3,D3) -> Juan Perez
A4: Con003 | B4: GAM | C4: Pedro | D4: Espanol | E4: Sutil | F4: lucas@gam.com | G4: 5695656585 | H4: =_xlfn.TEXTJOIN(" ", TRUE,C4,D4) -> Pedro Espanol
A5: Con004 | B5: BANCO DE CHILE | C5: Sheila | D5: Lafevre | E5: Perez | F5: sheila@banco.com | H5: =_xlfn.TEXTJOIN(" ", TRUE,C5,D5) -> Sheila Lafevre
A6: Con005 | H6: =_xlfn.TEXTJOIN(" ", TRUE,C6,D6)
A7: Con006 | H7: =_xlfn.TEXTJOIN(" ", TRUE,C7,D7)
A8: Con007 | H8: =_xlfn.TEXTJOIN(" ", TRUE,C8,D8)
H9: =_xlfn.TEXTJOIN(" ", TRUE,C9,D9)
H10: =_xlfn.TEXTJOIN(" ", TRUE,C10,D10)

Sheet Seguros
A1: ID_Seguro | B1: Polizas | C1: Link
A2: SEG001 | B2: POLIZA 223 HDI
A3: SEG002
A4: SEG003
A5: SEG004
A6: SEG005
A7: SEG006
A8: SEG007
A9: SEG008
A10: SEG009

Sheet Ubicacion
A1: ID_Ubicacion | B1: Cliente | C1: Ubicacion
A2: U001 | B2: BODEGAS SAN FRANCISCO LIMITADA | C2: Puerto Madero
A3: U002 | B3: BODEGAS SAN FRANCISCO LIMITADA | C3: Bodega 10
A4: U003 | B4: FALABELLA | C4: Bodega 15
A5: U004 | B5: DOMINIQUE HIRIART
A6: U005
A7: U006
A8: U007
A9: U008
A10: U009

Sheet Facturacion
A1: ID_Movimiento | B1: Ingreso Egreso | C1: Empresa | D1: Concepto | E1: Detalle | F1: Facturas | G1: Monto_Neto | H1: Monto_Con_IVA | I1: Estado | J1: Fecha_Emision_Factura | K1: Fecha_De_Pago | L1: ReferenciaFacturas | P1: -----INGRESOS-----
A2: MOV001 | B2: Ingreso | C2: BODEGAS SAN FRANCISCO LIMITADA | D2: Venta | F2: 201 | G2: 900000 | H2: =+Facturacion[[#This Row],[Monto_Neto]]*1.19 -> 1071000 | I2: Facturado | J2: 45881 | L2: =_xlfn.TEXTJOIN(" - ", TRUE,Facturacion[[#This Row],[Ingreso Egreso]],TEXT(J2, "dd-mmm-yyyy"), A2, C2,F2 ) -> Ingreso - 12-Aug-2025 - MOV001 - BODEGAS SAN FRANCISCO LIMITADA - 201 | P2: Venta
A3: MOV002 | B3: Egreso | C3: BODEGAS SAN FRANCISCO LIMITADA | D3: Arriendo Oficina | F3: 5213 | G3: 650000 | H3: =+Facturacion[[#This Row],[Monto_Neto]]*1.19 -> 773500 | I3: Pagado | J3: 45881 | K3: 45945 | L3: =_xlfn.TEXTJOIN(" - ", TRUE,Facturacion[[#This Row],[Ingreso Egreso]],TEXT(J3, "dd-mmm-yyyy"), A3, C3,F3 ) -> Egreso - 12-Aug-2025 - MOV002 - BODEGAS SAN FRANCISCO LIMITADA - 5213 | P3: Reembolsos
A4: MOV003 | B4: Egreso | C4: HORIZON | D4: Sub-arriendos | F4: 6523 | G4: 1000000 | H4: =+Facturacion[[#This Row],[Monto_Neto]]*1.19 -> 1190000 | I4: Por cobrar | L4: =_xlfn.TEXTJOIN(" - ", TRUE,Facturacion[[#This Row],[Ingreso Egreso]],TEXT(J4, "dd-mmm-yyyy"), A4, C4,F4 ) -> Egreso - 00-Jan-1900 - MOV003 - HORIZON - 6523 | P4: Otros Ingresos
A5: MOV004 | B5: Ingreso | C5: FALABELLA | D5: Arriendo Oficina | F5: 3265 | G5: 2300000 | H5: =+Facturacion[[#This Row],[Monto_Neto]]*1.19 -> 2737000 | I5: Por cobrar | L5: =_xlfn.TEXTJOIN(" - ", TRUE,Facturacion[[#This Row],[Ingreso Egreso]],TEXT(J5, "dd-mmm-yyyy"), A5, C5,F5 ) -> Ingreso - 00-Jan-1900 - MOV004 - FALABELLA - 3265 | P5: Prestamos socios
A6: MOV005 | H6: =+Facturacion[[#This Row],[Monto_Neto]]*1.19 -> 0
A7: MOV006 | H7: =+Facturacion[[#This Row],[Monto_Neto]]*1.19 -> 0 | P7: -----EGRESOS-----
A8: MOV007 | H8: =+Facturacion[[#This Row],[Monto_Neto]]*1.19 -> 0 | P8: Arriendo Oficina
A9: MOV008 | H9: =+Facturacion[[#This Row],[Monto_Neto]]*1.19 -> 0 | P9: Cotizaciones Previsionales
A10: MOV009 | H10: =+Facturacion[[#This Row],[Monto_Neto]]*1.19 -> 0 | P10: Gastos administrativos
P11: Impuestos
P12: Mantencion Cta Cte
P13: Otros Gastos
P14: Pago cuota leasing
P15: Remuneraciones
P16: Seguros
P17: Servicio Tecnico
P18: Sub-arriendos
P19: Transportes

Sheet Prestamos Directos
A1: ID_CreditoDirecto | B1: Fecha prestamo | C1: Acreedor | D1: Monto | E1: N°Cuotas | F1: Tasa | G1: Cuota UF | H1: Fecha Termino | I1: Pendientes | J1: Comentarios
A2: CD001 | B2: 45828 | C2: DOMINIQUE HIRIART | D2: =92000000/39202.08 -> 2346.8143 | E2: 48 | F2: 0.08 | G2: =-PMT(Financiamiento[[#This Row],[Tasa]]/12,Financiamiento[[#This Row],[N°Cuotas]],Financiamiento[[#This Row],[Monto]]) -> 57.292594 | H2: =EDATE(Financiamiento[[#This Row],[Fecha prestamo]], Financiamiento[[#This Row],[N°Cuotas]]) -> 47289 | I2: =DATEDIF(TODAY(),Financiamiento[[#This Row],[Fecha Termino]],"m")+1 -> 45
A3: CD002 | G3: =-PMT(Financiamiento[[#This Row],[Tasa]]/12,Financiamiento[[#This Row],[N°Cuotas]],Financiamiento[[#This Row],[Monto]]) -> #NUM! | H3: =EDATE(Financiamiento[[#This Row],[Fecha prestamo]], Financiamiento[[#This Row],[N°Cuotas]]) -> 0 | I3: =DATEDIF(TODAY(),Financiamiento[[#This Row],[Fecha Termino]],"m")+1 -> #NUM!
A4: CD003 | G4: =-PMT(Financiamiento[[#This Row],[Tasa]]/12,Financiamiento[[#This Row],[N°Cuotas]],Financiamiento[[#This Row],[Monto]]) -> #NUM! | H4: =EDATE(Financiamiento[[#This Row],[Fecha prestamo]], Financiamiento[[#This Row],[N°Cuotas]]) -> 0 | I4: =DATEDIF(TODAY(),Financiamiento[[#This Row],[Fecha Termino]],"m")+1 -> #NUM!
A5: CD004 | G5: =-PMT(Financiamiento[[#This Row],[Tasa]]/12,Financiamiento[[#This Row],[N°Cuotas]],Financiamiento[[#This Row],[Monto]]) -> #NUM! | H5: =EDATE(Financiamiento[[#This Row],[Fecha prestamo]], Financiamiento[[#This Row],[N°Cuotas]]) -> 0 | I5: =DATEDIF(TODAY(),Financiamiento[[#This Row],[Fecha Termino]],"m")+1 -> #NUM!
A6: CD005 | G6: =-PMT(Financiamiento[[#This Row],[Tasa]]/12,Financiamiento[[#This Row],[N°Cuotas]],Financiamiento[[#This Row],[Monto]]) -> #NUM! | H6: =EDATE(Financiamiento[[#This Row],[Fecha prestamo]], Financiamiento[[#This Row],[N°Cuotas]]) -> 0 | I6: =DATEDIF(TODAY(),Financiamiento[[#This Row],[Fecha Termino]],"m")+1 -> #NUM!
A7: CD006 | G7: =-PMT(Financiamiento[[#This Row],[Tasa]]/12,Financiamiento[[#This Row],[N°Cuotas]],Financiamiento[[#This Row],[Monto]]) -> #NUM! | H7: =EDATE(Financiamiento[[#This Row],[Fecha prestamo]], Financiamiento[[#This Row],[N°Cuotas]]) -> 0 | I7: =DATEDIF(TODAY(),Financiamiento[[#This Row],[Fecha Termino]],"m")+1 -> #NUM!
A8: CD007 | G8: =-PMT(Financiamiento[[#This Row],[Tasa]]/12,Financiamiento[[#This Row],[N°Cuotas]],Financiamiento[[#This Row],[Monto]]) -> #NUM! | H8: =EDATE(Financiamiento[[#This Row],[Fecha prestamo]], Financiamiento[[#This Row],[N°Cuotas]]) -> 0 | I8: =DATEDIF(TODAY(),Financiamiento[[#This Row],[Fecha Termino]],"m")+1 -> #NUM!
A9: CD008 | G9: =-PMT(Financiamiento[[#This Row],[Tasa]]/12,Financiamiento[[#This Row],[N°Cuotas]],Financiamiento[[#This Row],[Monto]]) -> #NUM! | H9: =EDATE(Financiamiento[[#This Row],[Fecha prestamo]], Financiamiento[[#This Row],[N°Cuotas]]) -> 0 | I9: =DATEDIF(TODAY(),Financiamiento[[#This Row],[Fecha Termino]],"m")+1 -> #NUM!
A10: CD009 | G10: =-PMT(Financiamiento[[#This Row],[Tasa]]/12,Financiamiento[[#This Row],[N°Cuotas]],Financiamiento[[#This Row],[Monto]]) -> #NUM! | H10: =EDATE(Financiamiento[[#This Row],[Fecha prestamo]], Financiamiento[[#This Row],[N°Cuotas]]) -> 0 | I10: =DATEDIF(TODAY(),Financiamiento[[#This Row],[Fecha Termino]],"m")+1 -> #NUM!

Sheet Leasing
A1: ID_Leasing | B1: Fecha | C1: Equipo | D1: Acreedor | E1: N°Cuotas | F1: Pie neto | G1: Cuota neta | H1: Cuota con IVA | I1: Fecha Termino | J1: Cuotas pendientes
A2: L001 | B2: 45828 | C2: E027 - Grua Horquilla - TOYOTA | D2: BANCO DE CHILE | E2: 49 | F2: 10000000 | G2: 465000 | H2: =+Financiamiento14[[#This Row],[Cuota neta]]*1.19 -> 553350 | I2: =EDATE(Financiamiento14[[#This Row],[Fecha]], Financiamiento14[[#This Row],[N°Cuotas]]) -> 47319 | J2: =DATEDIF(TODAY(),Financiamiento14[[#This Row],[Fecha Termino]],"m")+1 -> 46
A3: L002
A4: L003
A5: L004
A6: L005 | H6: =+Financiamiento14[[#This Row],[Cuota neta]]*1.19 -> 0
A7: L006 | H7: =+Financiamiento14[[#This Row],[Cuota neta]]*1.19 -> 0
A8: L007 | H8: =+Financiamiento14[[#This Row],[Cuota neta]]*1.19 -> 0
A9: L008 | H9: =+Financiamiento14[[#This Row],[Cuota neta]]*1.19 -> 0
A10: L009 | H10: =+Financiamiento14[[#This Row],[Cuota neta]]*1.19 -> 0

Sheet UF
B1: UF
A2: Julio 2025 | B2: 39184.08
